project4bim2022g2/__init___.py
project4bim2022g2/autoencoder.py
project4bim2022g2/genetic_algorithm.py
project4bim2022g2/robot_portrait.py
project4bim2022g2/utils.py
project4bim2022g2/model_vae/VAE_decoder2.data-00000-of-00001
project4bim2022g2/model_vae/VAE_decoder2.index
project4bim2022g2/model_vae/VAE_decoder6.data-00000-of-00001
project4bim2022g2/model_vae/VAE_decoder6.index
project4bim2022g2/model_vae/VAE_encoder2.data-00000-of-00001
project4bim2022g2/model_vae/VAE_encoder2.index
project4bim2022g2/model_vae/VAE_encoder6.data-00000-of-00001
project4bim2022g2/model_vae/VAE_encoder6.index
project4bim2022_g2-1.0.0.dist-info/LICENSE
project4bim2022_g2-1.0.0.dist-info/METADATA
project4bim2022_g2-1.0.0.dist-info/WHEEL
project4bim2022_g2-1.0.0.dist-info/top_level.txt
project4bim2022_g2-1.0.0.dist-info/RECORD
